geodepy/__init__.py
geodepy/angles.py
geodepy/constants.py
geodepy/convert.py
geodepy/coord.py
geodepy/fileio.py
geodepy/geodesy.py
geodepy/gnss.py
geodepy/height.py
geodepy/inputoutput.py
geodepy/ntv2reader.py
geodepy/statistics.py
geodepy/survey.py
geodepy/transform.py
geodepy-0.6.0.dist-info/LICENSE
geodepy-0.6.0.dist-info/METADATA
geodepy-0.6.0.dist-info/WHEEL
geodepy-0.6.0.dist-info/top_level.txt
geodepy-0.6.0.dist-info/RECORD
